Metadata-Version: 2.1
Name: localizator
Version: 0.1.0
Summary: Easy to use abstractions for localizing your python apps.
Home-page: https://github.com/yegorf1/localizator
Author: YogurtTheHorse
Author-email: yogurt@yogurtthehor.se
License: UNKNOWN
Platform: UNKNOWN
Classifier: Programming Language :: Python :: 3
Classifier: License :: OSI Approved :: MIT License
Classifier: Operating System :: OS Independent
